drawly/__init__.py
drawly/drawly.py
drawly-1.1.6.dist-info/licenses/LICENSE
drawly-1.1.6.dist-info/METADATA
drawly-1.1.6.dist-info/WHEEL
drawly-1.1.6.dist-info/top_level.txt
drawly-1.1.6.dist-info/RECORD
