Metadata-Version: 2.4
Name: drawly
Version: 1.1.6
Summary: A small package to get started drawing pictures in CS1400
Author-email: Erik Falor <erik.falor@usu.edu>
Project-URL: Homepage, https://engineering.usu.edu/cs/
Classifier: Programming Language :: Python :: 3
Classifier: License :: OSI Approved :: MIT License
Classifier: Operating System :: OS Independent
Requires-Python: >=3.10
License-File: LICENSE
Requires-Dist: pygame>=2.5
Dynamic: license-file
